dhivatars/__init__.py
dhivatars/data/MV_Faseyha.otf
dhivatars/data/Mv_Eamaan_XP.otf
dhivatars-0.3.dist-info/LICENSE
dhivatars-0.3.dist-info/METADATA
dhivatars-0.3.dist-info/WHEEL
dhivatars-0.3.dist-info/top_level.txt
dhivatars-0.3.dist-info/RECORD
