Metadata-Version: 2.1
Name: dhivatars
Version: 0.3
Summary: Generates avatars from dhivehi names or strings
Home-page: https://github.com/phoenixatom/dhivehi-avatar
Author: Mohamed Aruham
Author-email: aruham@baivaru.net
License: GPLv3
Platform: UNKNOWN
Classifier: Programming Language :: Python
Classifier: Operating System :: OS Independent
Classifier: Intended Audience :: Developers
Requires-Dist: pillow
